mbo/__init__.py
mbo/algorithm/__init__.py
mbo/algorithm/algorithm.py
mbo/algorithm/random.py
test/__init__.py
test/test_algorithm.py
test/test_random.py
mbo-0.1.1.dist-info/LICENSE
mbo-0.1.1.dist-info/METADATA
mbo-0.1.1.dist-info/WHEEL
mbo-0.1.1.dist-info/top_level.txt
mbo-0.1.1.dist-info/RECORD
